{
    "optionName": "Intel Core i7-14700K",
    "modelPrefab": "IntelCPU",
    "modelPrefabForScaling": "IntelCPU",
    "detailedDescription": "The Intel Intel Core i7-14700K is a high-end processor with 20 cores and 28 threads. With a boost clock of 5.6GHz and 125W TDP, it delivers solid performance for gaming and productivity.",
    "frequency": "3.4 / 5.6 GHz",
    "wattage": "125W",
    "additionalSpecs": "LGA1700 | 20 Cores, 28 Threads | 125W TDP | 5.6GHz Max",
    "price": 420,
    "powerDraw": 125,
    "socket": "LGA1700",
    "ramType": "",
    "thermalOutput": 137,
    "coolerPerformance": 0,
    "fpsContribution": 85,
    "renderContribution": 85,
    "bootTimeReduction": 0,
    "bootTimeSec": 0,
    "singleCoreScore": 3500,
    "multiCoreScore": 32000,
    "maxWattage": 0,
    "efficiency": 0,
    "noiseLevelDb": 0
}